{
    "file_name": "scan20_jpg.rf.99cfc98d6c2cfa579e18cfc9f0aeefe2.jpg",
    "annotations": [
        {
            "id": 1,
            "image_id": 34,
            "category_id": 1,
            "bbox": [
                38,
                17,
                309,
                215
            ],
            "area": 53658,
            "segmentation": [],
            "iscrowd": 0
        },
        {
            "id": 2,
            "image_id": 34,
            "category_id": 1,
            "bbox": [
                305,
                22,
                614.5,
                220
            ],
            "area": 61281,
            "segmentation": [],
            "iscrowd": 0
        },
        {
            "id": 3,
            "image_id": 34,
            "category_id": 1,
            "bbox": [
                29,
                216,
                281.5,
                404
            ],
            "area": 47470,
            "segmentation": [],
            "iscrowd": 0
        },
        {
            "id": 4,
            "image_id": 34,
            "category_id": 1,
            "bbox": [
                282,
                223,
                618.5,
                405.5
            ],
            "area": 61411.25,
            "segmentation": [],
            "iscrowd": 0
        },
        {
            "id": 5,
            "image_id": 34,
            "category_id": 1,
            "bbox": [
                30,
                413,
                303.5,
                607
            ],
            "area": 53059,
            "segmentation": [],
            "iscrowd": 0
        },
        {
            "id": 6,
            "image_id": 34,
            "category_id": 1,
            "bbox": [
                307,
                416,
                476,
                608
            ],
            "area": 32448,
            "segmentation": [],
            "iscrowd": 0
        },
        {
            "id": 7,
            "image_id": 34,
            "category_id": 1,
            "bbox": [
                471,
                412,
                607.5,
                603.5
            ],
            "area": 26139.75,
            "segmentation": [],
            "iscrowd": 0
        }
    ]
}