{
    "file_name": "scan38_jpg.rf.f2a420165473433d02b5defe6e8df5dd.jpg",
    "annotations": [
        {
            "id": 1,
            "image_id": 26,
            "category_id": 1,
            "bbox": [
                24,
                15,
                220,
                211
            ],
            "area": 38416,
            "segmentation": [],
            "iscrowd": 0
        },
        {
            "id": 2,
            "image_id": 26,
            "category_id": 1,
            "bbox": [
                224,
                15,
                417.5,
                217
            ],
            "area": 39087,
            "segmentation": [],
            "iscrowd": 0
        },
        {
            "id": 3,
            "image_id": 26,
            "category_id": 1,
            "bbox": [
                416,
                16,
                601.5,
                216.5
            ],
            "area": 37192.75,
            "segmentation": [],
            "iscrowd": 0
        },
        {
            "id": 4,
            "image_id": 26,
            "category_id": 1,
            "bbox": [
                26,
                211,
                227.5,
                403.5
            ],
            "area": 38788.75,
            "segmentation": [],
            "iscrowd": 0
        },
        {
            "id": 5,
            "image_id": 26,
            "category_id": 1,
            "bbox": [
                175,
                215,
                407,
                403
            ],
            "area": 43616,
            "segmentation": [],
            "iscrowd": 0
        },
        {
            "id": 6,
            "image_id": 26,
            "category_id": 1,
            "bbox": [
                406,
                218,
                615,
                403.5
            ],
            "area": 38769.5,
            "segmentation": [],
            "iscrowd": 0
        },
        {
            "id": 7,
            "image_id": 26,
            "category_id": 1,
            "bbox": [
                30,
                406,
                252.5,
                603
            ],
            "area": 43832.5,
            "segmentation": [],
            "iscrowd": 0
        },
        {
            "id": 8,
            "image_id": 26,
            "category_id": 1,
            "bbox": [
                267,
                410,
                598,
                609
            ],
            "area": 65869,
            "segmentation": [],
            "iscrowd": 0
        }
    ]
}