{
    "file_name": "scan18_jpg.rf.87e35b67006df680fa9bff3e8620b6e7.jpg",
    "annotations": [
        {
            "id": 1,
            "image_id": 21,
            "category_id": 1,
            "bbox": [
                32,
                43,
                493.5,
                305
            ],
            "area": 120913,
            "segmentation": [],
            "iscrowd": 0
        },
        {
            "id": 2,
            "image_id": 21,
            "category_id": 1,
            "bbox": [
                495,
                30,
                621.5,
                222
            ],
            "area": 24288,
            "segmentation": [],
            "iscrowd": 0
        },
        {
            "id": 3,
            "image_id": 21,
            "category_id": 1,
            "bbox": [
                36,
                230,
                350,
                417
            ],
            "area": 58718,
            "segmentation": [],
            "iscrowd": 0
        },
        {
            "id": 4,
            "image_id": 21,
            "category_id": 1,
            "bbox": [
                315,
                228,
                626,
                453
            ],
            "area": 69975,
            "segmentation": [],
            "iscrowd": 0
        },
        {
            "id": 5,
            "image_id": 21,
            "category_id": 1,
            "bbox": [
                47,
                421,
                304.5,
                602
            ],
            "area": 46607.5,
            "segmentation": [],
            "iscrowd": 0
        },
        {
            "id": 6,
            "image_id": 21,
            "category_id": 1,
            "bbox": [
                316,
                448,
                616.5,
                607.5
            ],
            "area": 47929.75,
            "segmentation": [],
            "iscrowd": 0
        }
    ]
}